PhoneCreate/__init__.py
PhoneCreate/phone.py
PhoneCreate-0.0.2.dist-info/LICENSE
PhoneCreate-0.0.2.dist-info/METADATA
PhoneCreate-0.0.2.dist-info/WHEEL
PhoneCreate-0.0.2.dist-info/top_level.txt
PhoneCreate-0.0.2.dist-info/RECORD
